{
  "coverage": 0.5145252372358387,
  "grid_h": 150,
  "grid_w": 216,
  "height_m": 18.0,
  "known": [
    "????????????????????????????????????????????????????????????????????????????????????????????????????????????????????????????????????????????????????????????????????????????????????????????????????????????????????????",
    "????????????????????????????????????????????????????????????????????????????????????????????????????????????????????????????????????????????????????????????????????????????????????????????????????????????????????????",
    "????????????????????????????????????????????????????????????????????????????????????????????????????????????????????????????????????????????????????????????????????????????????????????????????????????????????????????",
    "????????????????????????????????????????????????????????????????????????????????????????????????????????????????????????????????????????????????????????????????????????????????????????????????????????????????????????",
    "????????????????????????????????????????????????????????????????????????????????????????????????????????????????????????????????????????????????????????????????????????????????????????????????????????????????????????",
    "?????##################################################################################################################################################?#?##????????????????????????????????????????????????????????????",
    "?????#........................................................................................................................................................??????????????????????????????????????????????????????????",
    "?????#........................................................................................................................................................??????????????????????????????????????????????????????????",
    "?????#........................................................................................................................................................??????????????????????????????????????????????????????????",
    "?????#........................................................................................................................................................??????????????????????????????????????????????????????????",
    "?????#........................................................................................................................................................??????????????????????????????????????????????????????????",
    "?????#........................................................................................................................................................??????????????????????????????????????????????????????????",
    "?????#........................................................................................................................................................??????????????????????????????????????????????????????????",
    "?????#....................................................#############.......................................................................................??????????????????????????????????????????????????????????",
    "?????#...........................................##########??????????##.....................###############..................................................???????????????????????????????????????????????????????????",
    "?????#...........................................#??????????????????###.....................#?????????????#..................................................???????????????????????????????????????????????????????????",
    "?????#...........................................#?????????????????####.....................#?????????????#..................................................???????????????????????????????????????????????????????????",
    "?????#...........................................#????????????????#####.....................#?????????????#..................................................???????????????????????????????????????????????????????????",
    "?????#...........................................#???????????????######.....................#?????????????#..................................................???????????????????????????????????????????????????????????",
    "?????#.........................###################??????????????#####?############...########????????????####...............................................????????????????????????????????????????????????????????????",
    "?????#.........................#???????????????????????????????#####?????????????#...#??????????????????#####...............................................????????????????????????????????????????????????????????????",
    "?????#.........................#??????????????????????????????#####???????????????...#?????????????????######..............................................?????????????????????????????????????????????????????????????",
    "?????#.........................#?????????????????????????????#####???????????????#...?????????????????#####?#..............................................?????????????????????????????????????????????????????????????",
    "?????#.........................#?????????????????????????????####????????????????#...????????????????#####??#..............................................?????????????????????????????????????????????????????????????",
    "?????#.........................#?????????????????????????????###?????????????????#...???????????????#####???#.............................................??????????????????????????????????????????????????????????????",
    "?????#.........................#?????????????????????????????###?????????????????#...#?????????????#####????#.............................................??????????????????????????????????????????????????????????????",
    "?????#.........................#?????????????????????????????###?????????????????#...?????????????#####?????###..........................................???????????????????????????????????????????????????????????????",
    "?????#.........................#???????????????????????####?####?????????????????#...????????????#####????????#..........................................???????????????????????????????????????????????????????????????",
    "?????#.........................#???????????????????????#..######?????????????????#...???????????#####?????????#.........................................????????????????????????????????????????????????????????????????",
    "?????#.........................#???????????????????????#..#####??????????????????#...??????????#####??????????#.........................................????????????????????????????????????????????????????????????????",
    "?????#.........................#???????????????????????#..####???????????????????#...#????????#####????????????........................................?????????????????????????????????????????????????????????????????",
    "?????#.........................#???????????????????????#..###????????????????????#...#???????#####?????????????........................................?????????????????????????????????????????????????????????????????",
    "?????#.........................#???????????????????????#..##?????????????????????#...???????#####??????????????........................................?????????????????????????????????????????????????????????????????",
    "?????#.........................#???????????????????????#..##????????????##########...##############???????????#.......................................??????????????????????????????????????????????????????????????????",
    "?????#.........................#########################...#????????????#.........................#???????????#.......................................??????????????????????????????????????????????????????????????????",
    "?????#.....................................................#????????????#.........................#????????????......................................???????????????????????????????????????????????????????????????????",
    "?????#.....................................................#????????????#.........................#???????????#......................................???????????????????????????????????????????????????????????????????",
    "?????#.....................................................#????????????#.........................#???????????#.....................................????????????????????????????????????????????????????????????????????",
    "?????#.....................................................#????????????#.........................####?###?#?##.....................................????????????????????????????????????????????????????????????????????",
    "?????#.....................................................#????????????#..........................................................................?????????????????????????????????????????????????????????????????????",
    "?????#.....................................................#????????????#..................................................................#######??????????????????????????????????????????????????????????????????????",
    "?????#...................................................###????????????###########............................#########################...#????????????????????????????????????????????????????????????????????????????",
    "?????#...................................................#????????????????????????#............................#????????????????????????...#????????????????????????????????????????????????????????????????????????????",
    "?????#...................................................#???????????????????????##............................#?????????????????????????..#????????????????????????????????????????????????????????????????????????????",
    "?????#...................................................#??????????????????????###............................#??????????????????????????.#????????????????????????????????????????????????????????????????????????????",
    "?????#...................................................#?????????????????????####............................#????????????????????????????????????????????????????????????????????????????????????????????????????????",
    "?????#...................................................#????????????????????#####............................#????????????????????????????????????????????????????????????????????????????????????????????????????????",
    "?????#...................................................#???????????????????######............................#????????????????????????????????????????????????????????????????????????????????????????????????????????",
    "?????#...................................................#??????????????????#####?#............................#????????????????????????????????????????????????????????????????????????????????????????????????????????",
    "?????#...................................................#?????????????????#####??#............................#????????????????????????????????????????????????????????????????????????????????????????????????????????",
    "?????#...................................................#????????????????#####???#............................#????????????????????????????????????????????????????????????????????????????????????????????????????????",
    "?????#...................................................#???????????????#####????#............................#????????????????????????????????????????????????????????????????????????????????????????????????????????",
    "?????#...................................................#??????????????#####?????#######......................#????????????????????????????????????????????????????????????????????????????????????????????????????????",
    "?????#...................................................#?????????????#####?????????????......................#????????????????????????????????????????????????????????????????????????????????????????????????????????",
    "?????#...................................................#?????????????####?????????????#......................#????????????????????????????????????????????????????????????????????????????????????????????????????????",
    "?????#...................................................##################?????????????#.........................??????????????????????????????????????????????????????????????????????????????????????????????????????",
    "?????#....................................................................#??????????????............................???????????????????????????????????????????????????????????????????????????????????????????????????",
    "?????#....................................................................#??????????????..........................?....????????????????????????????????????????????????????????????????????????????????????????????????",
    "?????#....................................................................#??????????????............................?....??????????????????????????????????????????????????????????????????????????????????????????????",
    "?????#....................................................................#?????????????#..................................?????????????????????????????????????????????????????????????????????????????????????????????",
    "?????#....................................................................#??????????????......................?............????????????????????????????????????????????????????????????????????????????????????????????",
    "?????#....................................................................#?????????????#.....................?............?????????????????????????????????????????????????????????????????????????????????????????????",
    "?????#..........................#######################...#################??????????????####################?.############?????????????????????????????????????????????????????????????????????????????????????????????",
    "?????#..........................#?????????????????????#...#????????###????????????????????????????????????????.#????????????????????????????????????????????????????????????????????????????????????????????????????????",
    "?????#..........................#?????????????????????#...#????????###?????????????????????????????????????????#????????????????????????????????????????????????????????????????????????????????????????????????????????",
    "?????#..........................#?????????????????????#...#???????####??????????????????????????????????????????????????????????????????????????????????????????????????????????????????????????????????????????????????",
    "?????#..........................#?????????????????????#...#??????#####??????????????????????????????????????????????????????????????????????????????????????????????????????????????????????????????????????????????????",
    "?????#..........................#??????????????????????...#?????#####???????????????????????????????????????????????????????????????????????????????????????????????????????????????????????????????????????????????????",
    "?????#..........................#?????????????????????#...#????#####????????????????????????????????????????????????????????????????????????????????????????????????????????????????????????????????????????????????????",
    "?????#..........................#?????????????????????#...#???#####?????????????????????????????????????????????????????????????????????????????????????????????????????????????????????????????????????????????????????",
    "?????#..........................#?????????????????????#...#??#####??????????????????????????????????????????????????????????????????????????????????????????????????????????????????????????????????????????????????????",
    "?????#..........................#?????????????????????#...#?#####???????????????????????????????????????????????????????????????????????????????????????????????????????????????????????????????????????????????????????",
    "?????#..........................#?????????????????????#...######????????????????????????????????????????????????????????????????????????????????????????????????????????????????????????????????????????????????????????",
    "?????#..........................#?????????????????????#...#####?????????????????????????????????????????????????????????????????????????????????????????????????????????????????????????????????????????????????????????",
    "?????#..........................#?????????????????????#...####??????????????????????????????????????????????????????????????????????????????????????????????????????????????????????????????????????????????????????????",
    "?????#..........................#?????????????????????#...###???????????????????????????????????????????????????????????????????????????????????????????????????????????????????????????????????????????????????????????",
    "?????#..........................#????????????????????##...#?????????????????????????????????????????????????????????????????????????????????????????????????????????????????????????????????????????????????????????????",
    "?????#..........................#######################...##################??#???..##???#??????????????????????????????????????????????????????????????????????????????????????????????????????????????????????????????",
    "?????#...........................................................................................???????????????????????????????????????????????????????????????????????????????????????????????????????????????????????",
    "?????#........................................................................................??????????????????????????????????????????????????????????????????????????????????????????????????????????????????????????",
    "?????#...........................................................................................???????????????????????????????????????????????????????????????????????????????????????????????????????????????????????",
    "?????#........................................................................................??????????????????????????????????????????????????????????????????????????????????????????????????????????????????????????",
    "?????#...........................................................................................???????????????????????????????????????????????????????????????????????????????????????????????????????????????????????",
    "?????#..........................................................................................?.??????????????????????????????????????????????????????????????????????????????????????????????????????????????????????",
    "?????#...................................................#######################??#...#???##??###???????????????????????????????????????????????????????????????????????????????????????????????????????????????????????",
    "?????#...................................................#??????????????????????????????????????????????????????????????????????????????????????????????????????????????????????????????????????????????????????????????",
    "?????#...................................................#??????????????????????????????????????????????????????????????????????????????????????????????????????????????????????????????????????????????????????????????",
    "?????#...................................................#??????????????????????????????????????????????????????????????????????????????????????????????????????????????????????????????????????????????????????????????",
    "?????#...................................................#??????????????????????????????????????????????????????????????????????????????????????????????????????????????????????????????????????????????????????????????",
    "?????#...................................................#??????????????????????????????????????????????????????????????????????????????????????????????????????????????????????????????????????????????????????????????",
    "?????#...................................................#??????????????????????????????????????????????????????????????????????????????????????????????????????????????????????????????????????????????????????????????",
    "?????#...................................................#??????????????????????????????????????????????????????????????????????????????????????????????????????????????????????????????????????????????????????????????",
    "?????#...................................................#??????????????????????????????????????????????????????????????????????????????????????????????????????????????????????????????????????????????????????????????",
    "?????#...................................................#??????????????????????????????????????????????????????????????????????????????????????????????????????????????????????????????????????????????????????????????",
    "?????#...................................................#??????????????????????????????????????????????????????????????????????????????????????????????????????????????????????????????????????????????????????????????",
    "?????#...................................................#??????????????????????????????????????????????????????????????????????????????????????????????????????????????????????????????????????????????????????????????",
    "?????#...................................................#??????????????????????????????????????????????????????????????????????????????????????????????????????????????????????????????????????????????????????????????",
    "?????#...................................................#??????????????????????????????????????????????????????????????????????????????????????????????????????????????????????????????????????????????????????????????",
    "?????#...................................................#??????????????????????????????????????????????????????????????????????????????????????????????????????????????????????????????????????????????????????????????",
    "?????#...........................................................???????????????????????????????????????????????????????????????????????????????????????????????????????????????????????????????????????????????????????",
    "?????#...................................................................???????????????????????????????????????????????????????????????????????????????????????????????????????????????????????????????????????????????",
    "?????#...............................................................#####??????????????????????????????????????????????????????????????????????????????????????????????????????????????????????????????????????????????",
    "?????#...............................................................#??????????????????????????????????????????????????????????????????????????????????????????????????????????????????????????????????????????????????",
    "?????#...............................................................#??????????????????????????????????????????????????????????????????????????????????????????????????????????????????????????????????????????????????",
    "?????#...............................................................#??????????????????????????????????????????????????????????????????????????????????????????????????????????????????????????????????????????????????",
    "?????#...............................................................#??????????????????????????????????????????????????????????????????????????????????????????????????????????????????????????????????????????????????",
    "?????#.........................########################..............#??????????????????????????????????????????????????????????????????????????????????????????????????????????????????????????????????????????????????",
    "?????#.........................#???????????????????????..............#??????????????????????????????????????????????????????????????????????????????????????????????????????????????????????????????????????????????????",
    "?????#.........................#???????????????????????..............#??????????????????????????????????????????????????????????????????????????????????????????????????????????????????????????????????????????????????",
    "?????#.........................#???????????????????????..............#??????????????????????????????????????????????????????????????????????????????????????????????????????????????????????????????????????????????????",
    "?????#.........................#??????????????????????#..............#??????????????????????????????????????????????????????????????????????????????????????????????????????????????????????????????????????????????????",
    "?????#.........................#???????????????????????..............#??????????????????????????????????????????????????????????????????????????????????????????????????????????????????????????????????????????????????",
    "?????#.........................#???????????????????????..............#??????????????????????????????????????????????????????????????????????????????????????????????????????????????????????????????????????????????????",
    "?????#.........................#???????????????????????..............#??????????????????????????????????????????????????????????????????????????????????????????????????????????????????????????????????????????????????",
    "?????#.........................#???????????????????????..............#??????????????????????????????????????????????????????????????????????????????????????????????????????????????????????????????????????????????????",
    "?????#.........................#???????????????????????................?????????????????????????????????????????????????????????????????????????????????????????????????????????????????????????????????????????????????",
    "?????#.........................#???????????????????????.................????????????????????????????????????????????????????????????????????????????????????????????????????????????????????????????????????????????????",
    "?????#.........................#???????????????????????..................???????????????????????????????????????????????????????????????????????????????????????????????????????????????????????????????????????????????",
    "?????#.........................#???????????????????????..................???????????????????????????????????????????????????????????????????????????????????????????????????????????????????????????????????????????????",
    "?????#.........................#???????????????????????.................????????????????????????????????????????????????????????????????????????????????????????????????????????????????????????????????????????????????",
    "?????#..........................????????????????????????...............?????????????????????????????????????????????????????????????????????????????????????????????????????????????????????????????????????????????????",
    "?????#...........................????????????????????????.............??????????????????????????????????????????????????????????????????????????????????????????????????????????????????????????????????????????????????",
    "?????#...........................#????????????????????????##########????????????????????????????????????????????????????????????????????????????????????????????????????????????????????????????????????????????????????",
    "?????#...........................#??????????????????????????????????????????????????????????????????????????????????????????????????????????????????????????????????????????????????????????????????????????????????????",
    "?????#...........................#??????????????????????????????????????????????????????????????????????????????????????????????????????????????????????????????????????????????????????????????????????????????????????",
    "?????#...........................#??????????????????????????????????????????????????????????????????????????????????????????????????????????????????????????????????????????????????????????????????????????????????????",
    "?????#...........................#??????????????????????????????????????????????????????????????????????????????????????????????????????????????????????????????????????????????????????????????????????????????????????",
    "?????#...........................#??????????????????????????????????????????????????????????????????????????????????????????????????????????????????????????????????????????????????????????????????????????????????????",
    "?????#...........................#??????????????????????????????????????????????????????????????????????????????????????????????????????????????????????????????????????????????????????????????????????????????????????",
    "?????#...........................#??????????????????????????????????????????????????????????????????????????????????????????????????????????????????????????????????????????????????????????????????????????????????????",
    "?????#...........................#??????????????????????????????????????????????????????????????????????????????????????????????????????????????????????????????????????????????????????????????????????????????????????",
    "?????#...........................#??????????????????????????????????????????????????????????????????????????????????????????????????????????????????????????????????????????????????????????????????????????????????????",
    "?????#...........................#??????????????????????????????????????????????????????????????????????????????????????????????????????????????????????????????????????????????????????????????????????????????????????",
    "?????#...........................#??????????????????????????????????????????????????????????????????????????????????????????????????????????????????????????????????????????????????????????????????????????????????????",
    "?????#...........................#??????????????????????????????????????????????????????????????????????????????????????????????????????????????????????????????????????????????????????????????????????????????????????",
    "?????#...........................#??????????????????????????????????????????????????????????????????????????????????????????????????????????????????????????????????????????????????????????????????????????????????????",
    "?????#...........................???????????????????????????????????????????????????????????????????????????????????????????????????????????????????????????????????????????????????????????????????????????????????????",
    "?????#...........................???????????????????????????????????????????????????????????????????????????????????????????????????????????????????????????????????????????????????????????????????????????????????????",
    "??????............................??????????????????????????????????????????????????????????????????????????????????????????????????????????????????????????????????????????????????????????????????????????????????????",
    "??????.......................???????????????????????????????????????????????????????????????????????????????????????????????????????????????????????????????????????????????????????????????????????????????????????????",
    "?????#.....................?????????????????????????????????????????????????????????????????????????????????????????????????????????????????????????????????????????????????????????????????????????????????????????????",
    "??????...................???????????????????????????????????????????????????????????????????????????????????????????????????????????????????????????????????????????????????????????????????????????????????????????????",
    "??????.................?????????????????????????????????????????????????????????????????????????????????????????????????????????????????????????????????????????????????????????????????????????????????????????????????",
    "??????..............????????????????????????????????????????????????????????????????????????????????????????????????????????????????????????????????????????????????????????????????????????????????????????????????????",
    "??????########?#?#??????????????????????????????????????????????????????????????????????????????????????????????????????????????????????????????????????????????????????????????????????????????????????????????????????",
    "????????????????????????????????????????????????????????????????????????????????????????????????????????????????????????????????????????????????????????????????????????????????????????????????????????????????????????",
    "????????????????????????????????????????????????????????????????????????????????????????????????????????????????????????????????????????????????????????????????????????????????????????????????????????????????????????",
    "????????????????????????????????????????????????????????????????????????????????????????????????????????????????????????????????????????????????????????????????????????????????????????????????????????????????????????",
    "????????????????????????????????????????????????????????????????????????????????????????????????????????????????????????????????????????????????????????????????????????????????????????????????????????????????????????",
    "????????????????????????????????????????????????????????????????????????????????????????????????????????????????????????????????????????????????????????????????????????????????????????????????????????????????????????"
  ],
  "lidar": [
    {
      "x": 0.379999999999999,
      "y": -8.34
    },
    {
      "x": 0.379999999999999,
      "y": -8.34
    },
    {
      "x": 0.5,
      "y": -8.34
    },
    {
      "x": 0.5,
      "y": -8.34
    },
    {
      "x": 0.5,
      "y": -8.34
    },
    {
      "x": 0.5,
      "y": -8.34
    },
    {
      "x": 0.6199999999999992,
      "y": -8.34
    },
    {
      "x": 0.6199999999999992,
      "y": -8.34
    },
    {
      "x": 0.6199999999999992,
      "y": -8.34
    },
    {
      "x": 0.6199999999999992,
      "y": -8.34
    },
    {
      "x": 0.7400000000000002,
      "y": -8.34
    },
    {
      "x": 0.7400000000000002,
      "y": -8.34
    },
    {
      "x": 0.8599999999999994,
      "y": -8.34
    },
    {
      "x": 0.8599999999999994,
      "y": -8.34
    },
    {
      "x": 0.8599999999999994,
      "y": -8.34
    },
    {
      "x": 0.8599999999999994,
      "y": -8.34
    },
    {
      "x": 0.9799999999999986,
      "y": -8.34
    },
    {
      "x": 0.9799999999999986,
      "y": -8.34
    },
    {
      "x": 1.0999999999999996,
      "y": -8.34
    },
    {
      "x": 1.2199999999999989,
      "y": -8.34
    },
    {
      "x": 1.2199999999999989,
      "y": -8.34
    },
    {
      "x": 1.3399999999999999,
      "y": -8.34
    },
    {
      "x": 1.3399999999999999,
      "y": -8.34
    },
    {
      "x": 1.459999999999999,
      "y": -8.34
    },
    {
      "x": 1.58,
      "y": -8.34
    },
    {
      "x": 1.6999999999999993,
      "y": -8.34
    },
    {
      "x": 1.9399999999999995,
      "y": -8.34
    },
    {
      "x": 2.0599999999999987,
      "y": -8.34
    },
    {
      "x": 2.299999999999999,
      "y": -8.34
    },
    {
      "x": 2.539999999999999,
      "y": -8.34
    },
    {
      "x": 2.8999999999999986,
      "y": -8.34
    },
    {
      "x": 3.379999999999999,
      "y": -8.34
    },
    {
      "x": 4.219999999999999,
      "y": -8.34
    },
    {
      "x": 5.539999999999999,
      "y": -8.34
    },
    {
      "x": 4.219999999999999,
      "y": -4.140000000000001
    },
    {
      "x": 3.8599999999999994,
      "y": -4.140000000000001
    },
    {
      "x": 3.7399999999999984,
      "y": -4.0200000000000005
    },
    {
      "x": 3.7399999999999984,
      "y": -3.66
    },
    {
      "x": 3.1400000000000006,
      "y": -4.0200000000000005
    },
    {
      "x": 2.8999999999999986,
      "y": -4.0200000000000005
    },
    {
      "x": 2.66,
      "y": -4.0200000000000005
    },
    {
      "x": 2.539999999999999,
      "y": -4.0200000000000005
    },
    {
      "x": 2.299999999999999,
      "y": -4.0200000000000005
    },
    {
      "x": 2.0599999999999987,
      "y": -4.0200000000000005
    },
    {
      "x": 1.8200000000000003,
      "y": -4.0200000000000005
    },
    {
      "x": 1.6999999999999993,
      "y": -4.0200000000000005
    },
    {
      "x": 1.459999999999999,
      "y": -4.0200000000000005
    },
    {
      "x": 1.3399999999999999,
      "y": -4.0200000000000005
    },
    {
      "x": 1.2199999999999989,
      "y": -4.0200000000000005
    },
    {
      "x": 0.9799999999999986,
      "y": -4.0200000000000005
    },
    {
      "x": 0.8599999999999994,
      "y": -4.0200000000000005
    },
    {
      "x": 0.7400000000000002,
      "y": -4.0200000000000005
    },
    {
      "x": 0.5,
      "y": -4.0200000000000005
    },
    {
      "x": 0.379999999999999,
      "y": -4.0200000000000005
    },
    {
      "x": 0.2599999999999998,
      "y": -5.82
    },
    {
      "x": 0.2599999999999998,
      "y": -5.82
    },
    {
      "x": 0.1399999999999988,
      "y": -5.82
    },
    {
      "x": 0.019999999999999574,
      "y": -5.82
    },
    {
      "x": 0.019999999999999574,
      "y": -6.18
    },
    {
      "x": 0.019999999999999574,
      "y": -6.42
    },
    {
      "x": 0.019999999999999574,
      "y": -6.54
    },
    {
      "x": 0.019999999999999574,
      "y": -6.66
    },
    {
      "x": 0.019999999999999574,
      "y": -6.66
    },
    {
      "x": -0.09999999999999964,
      "y": -6.66
    },
    {
      "x": -0.09999999999999964,
      "y": -6.66
    },
    {
      "x": -0.22000000000000064,
      "y": -6.66
    },
    {
      "x": -0.22000000000000064,
      "y": -6.66
    },
    {
      "x": -0.22000000000000064,
      "y": -6.78
    },
    {
      "x": -0.22000000000000064,
      "y": -6.9
    },
    {
      "x": -0.22000000000000064,
      "y": -6.9
    },
    {
      "x": -0.22000000000000064,
      "y": -7.02
    },
    {
      "x": -0.22000000000000064,
      "y": -7.02
    },
    {
      "x": -0.22000000000000064,
      "y": -7.02
    },
    {
      "x": -0.22000000000000064,
      "y": -7.140000000000001
    },
    {
      "x": -0.22000000000000064,
      "y": -7.140000000000001
    },
    {
      "x": -0.22000000000000064,
      "y": -7.26
    },
    {
      "x": -0.22000000000000064,
      "y": -7.26
    },
    {
      "x": -0.22000000000000064,
      "y": -7.26
    },
    {
      "x": -0.22000000000000064,
      "y": -7.26
    },
    {
      "x": -0.22000000000000064,
      "y": -7.26
    },
    {
      "x": -0.33999999999999986,
      "y": -7.26
    },
    {
      "x": -0.5800000000000001,
      "y": -7.26
    },
    {
      "x": -0.7000000000000011,
      "y": -7.26
    },
    {
      "x": -0.8200000000000003,
      "y": -7.26
    },
    {
      "x": -1.0600000000000005,
      "y": -7.26
    },
    {
      "x": -1.42,
      "y": -7.26
    },
    {
      "x": -4.540000000000001,
      "y": -7.02
    },
    {
      "x": -4.540000000000001,
      "y": -7.140000000000001
    },
    {
      "x": -4.540000000000001,
      "y": -7.38
    },
    {
      "x": -4.780000000000001,
      "y": -8.34
    },
    {
      "x": -3.460000000000001,
      "y": -8.34
    },
    {
      "x": -2.620000000000001,
      "y": -8.34
    },
    {
      "x": -2.1400000000000006,
      "y": -8.34
    },
    {
      "x": -1.7800000000000011,
      "y": -8.34
    },
    {
      "x": -1.540000000000001,
      "y": -8.34
    },
    {
      "x": -1.3000000000000007,
      "y": -8.34
    },
    {
      "x": -1.1799999999999997,
      "y": -8.34
    },
    {
      "x": -0.9400000000000013,
      "y": -8.34
    },
    {
      "x": -0.8200000000000003,
      "y": -8.34
    },
    {
      "x": -0.7000000000000011,
      "y": -8.34
    },
    {
      "x": -0.5800000000000001,
      "y": -8.34
    },
    {
      "x": -0.5800000000000001,
      "y": -8.34
    },
    {
      "x": -0.46000000000000085,
      "y": -8.34
    },
    {
      "x": -0.46000000000000085,
      "y": -8.34
    },
    {
      "x": -0.33999999999999986,
      "y": -8.34
    },
    {
      "x": -0.22000000000000064,
      "y": -8.34
    },
    {
      "x": -0.22000000000000064,
      "y": -8.34
    },
    {
      "x": -0.09999999999999964,
      "y": -8.34
    },
    {
      "x": -0.09999999999999964,
      "y": -8.34
    },
    {
      "x": -0.09999999999999964,
      "y": -8.34
    },
    {
      "x": 0.019999999999999574,
      "y": -8.34
    },
    {
      "x": 0.019999999999999574,
      "y": -8.34
    },
    {
      "x": 0.019999999999999574,
      "y": -8.34
    },
    {
      "x": 0.1399999999999988,
      "y": -8.34
    },
    {
      "x": 0.1399999999999988,
      "y": -8.34
    },
    {
      "x": 0.1399999999999988,
      "y": -8.34
    },
    {
      "x": 0.1399999999999988,
      "y": -8.34
    },
    {
      "x": 0.2599999999999998,
      "y": -8.34
    },
    {
      "x": 0.2599999999999998,
      "y": -8.34
    },
    {
      "x": 0.2599999999999998,
      "y": -8.34
    },
    {
      "x": 0.2599999999999998,
      "y": -8.34
    },
    {
      "x": 0.379999999999999,
      "y": -8.34
    }
  ],
  "message": "frontier exploration",
  "origin": {
    "x": -13.0,
    "y": -9.0
  },
  "path": [
    {
      "x": 0.7400000000000002,
      "y": -8.22,
      "yaw": 0.0
    },
    {
      "x": 0.6199999999999992,
      "y": -8.1,
      "yaw": 0.0
    },
    {
      "x": 0.5,
      "y": -7.98,
      "yaw": 0.0
    },
    {
      "x": 0.379999999999999,
      "y": -7.86,
      "yaw": 0.0
    },
    {
      "x": 0.379999999999999,
      "y": -7.74,
      "yaw": 0.0
    },
    {
      "x": 0.379999999999999,
      "y": -7.62,
      "yaw": 0.0
    },
    {
      "x": 0.379999999999999,
      "y": -7.5,
      "yaw": 0.0
    },
    {
      "x": 0.379999999999999,
      "y": -7.38,
      "yaw": 0.0
    },
    {
      "x": 0.379999999999999,
      "y": -7.26,
      "yaw": 0.0
    },
    {
      "x": 0.379999999999999,
      "y": -7.140000000000001,
      "yaw": 0.0
    },
    {
      "x": 0.379999999999999,
      "y": -7.02,
      "yaw": 0.0
    },
    {
      "x": 0.379999999999999,
      "y": -6.9,
      "yaw": 0.0
    },
    {
      "x": 0.379999999999999,
      "y": -6.78,
      "yaw": 0.0
    },
    {
      "x": 0.379999999999999,
      "y": -6.66,
      "yaw": 0.0
    },
    {
      "x": 0.379999999999999,
      "y": -6.54,
      "yaw": 0.0
    },
    {
      "x": 0.379999999999999,
      "y": -6.42,
      "yaw": 0.0
    },
    {
      "x": 0.379999999999999,
      "y": -6.300000000000001,
      "yaw": 0.0
    },
    {
      "x": 0.379999999999999,
      "y": -6.18,
      "yaw": 0.0
    },
    {
      "x": 0.379999999999999,
      "y": -6.0600000000000005,
      "yaw": 0.0
    },
    {
      "x": 0.379999999999999,
      "y": -5.9399999999999995,
      "yaw": 0.0
    },
    {
      "x": 0.379999999999999,
      "y": -5.82,
      "yaw": 0.0
    },
    {
      "x": 0.379999999999999,
      "y": -5.7,
      "yaw": 0.0
    },
    {
      "x": 0.379999999999999,
      "y": -5.58,
      "yaw": 0.0
    },
    {
      "x": 0.379999999999999,
      "y": -5.46,
      "yaw": 0.0
    },
    {
      "x": 0.379999999999999,
      "y": -5.34,
      "yaw": 0.0
    },
    {
      "x": 0.2599999999999998,
      "y": -5.220000000000001,
      "yaw": 0.0
    },
    {
      "x": 0.1399999999999988,
      "y": -5.1,
      "yaw": 0.0
    },
    {
      "x": 0.019999999999999574,
      "y": -4.98,
      "yaw": 0.0
    },
    {
      "x": 0.019999999999999574,
      "y": -4.86,
      "yaw": 0.0
    },
    {
      "x": 0.019999999999999574,
      "y": -4.74,
      "yaw": 0.0
    },
    {
      "x": -0.09999999999999964,
      "y": -4.62,
      "yaw": 0.0
    },
    {
      "x": -0.22000000000000064,
      "y": -4.5,
      "yaw": 0.0
    },
    {
      "x": -0.22000000000000064,
      "y": -4.38,
      "yaw": 0.0
    },
    {
      "x": -0.22000000000000064,
      "y": -4.26,
      "yaw": 0.0
    },
    {
      "x": -0.33999999999999986,
      "y": -4.140000000000001,
      "yaw": 0.0
    },
    {
      "x": -0.46000000000000085,
      "y": -4.0200000000000005,
      "yaw": 0.0
    },
    {
      "x": -0.5800000000000001,
      "y": -3.9000000000000004,
      "yaw": 0.0
    },
    {
      "x": -0.7000000000000011,
      "y": -3.7800000000000002,
      "yaw": 0.0
    },
    {
      "x": -0.8200000000000003,
      "y": -3.66,
      "yaw": 0.0
    },
    {
      "x": -0.9400000000000013,
      "y": -3.54,
      "yaw": 0.0
    },
    {
      "x": -1.0600000000000005,
      "y": -3.42,
      "yaw": 0.0
    },
    {
      "x": -1.1799999999999997,
      "y": -3.3,
      "yaw": 0.0
    },
    {
      "x": -1.3000000000000007,
      "y": -3.1800000000000006,
      "yaw": 0.0
    },
    {
      "x": -1.42,
      "y": -3.0600000000000005,
      "yaw": 0.0
    },
    {
      "x": -1.540000000000001,
      "y": -2.9400000000000004,
      "yaw": 0.0
    },
    {
      "x": -1.6600000000000001,
      "y": -2.8200000000000003,
      "yaw": 0.0
    },
    {
      "x": -1.7800000000000011,
      "y": -2.7,
      "yaw": 0.0
    },
    {
      "x": -1.9000000000000004,
      "y": -2.58,
      "yaw": 0.0
    },
    {
      "x": -2.0199999999999996,
      "y": -2.46,
      "yaw": 0.0
    },
    {
      "x": -2.1400000000000006,
      "y": -2.34,
      "yaw": 0.0
    },
    {
      "x": -2.26,
      "y": -2.2200000000000006,
      "yaw": 0.0
    },
    {
      "x": -2.380000000000001,
      "y": -2.1000000000000005,
      "yaw": 0.0
    },
    {
      "x": -2.5,
      "y": -1.9800000000000004,
      "yaw": 0.0
    },
    {
      "x": -2.620000000000001,
      "y": -1.8600000000000003,
      "yaw": 0.0
    },
    {
      "x": -2.74,
      "y": -1.7400000000000002,
      "yaw": 0.0
    },
    {
      "x": -2.860000000000001,
      "y": -1.62,
      "yaw": 0.0
    },
    {
      "x": -2.9800000000000004,
      "y": -1.5,
      "yaw": 0.0
    },
    {
      "x": -3.0999999999999996,
      "y": -1.38,
      "yaw": 0.0
    },
    {
      "x": -3.2200000000000006,
      "y": -1.2600000000000007,
      "yaw": 0.0
    },
    {
      "x": -3.34,
      "y": -1.1400000000000006,
      "yaw": 0.0
    },
    {
      "x": -3.34,
      "y": -1.0200000000000005,
      "yaw": 0.0
    },
    {
      "x": -3.34,
      "y": -0.9000000000000004,
      "yaw": 0.0
    },
    {
      "x": -3.34,
      "y": -0.7800000000000011,
      "yaw": 0.0
    },
    {
      "x": -3.34,
      "y": -0.6600000000000001,
      "yaw": 0.0
    },
    {
      "x": -3.34,
      "y": -0.5400000000000009,
      "yaw": 0.0
    },
    {
      "x": -3.34,
      "y": -0.41999999999999993,
      "yaw": 0.0
    },
    {
      "x": -3.34,
      "y": -0.3000000000000007,
      "yaw": 0.0
    },
    {
      "x": -3.34,
      "y": -0.17999999999999972,
      "yaw": 0.0
    },
    {
      "x": -3.34,
      "y": -0.0600000000000005,
      "yaw": 0.0
    },
    {
      "x": -3.34,
      "y": 0.0600000000000005,
      "yaw": 0.0
    },
    {
      "x": -3.34,
      "y": 0.17999999999999972,
      "yaw": 0.0
    },
    {
      "x": -3.34,
      "y": 0.29999999999999893,
      "yaw": 0.0
    },
    {
      "x": -3.34,
      "y": 0.41999999999999993,
      "yaw": 0.0
    },
    {
      "x": -3.34,
      "y": 0.5399999999999991,
      "yaw": 0.0
    },
    {
      "x": -3.34,
      "y": 0.6600000000000001,
      "yaw": 0.0
    },
    {
      "x": -3.34,
      "y": 0.7799999999999994,
      "yaw": 0.0
    },
    {
      "x": -3.34,
      "y": 0.9000000000000004,
      "yaw": 0.0
    },
    {
      "x": -3.34,
      "y": 1.0199999999999996,
      "yaw": 0.0
    },
    {
      "x": -3.34,
      "y": 1.1399999999999988,
      "yaw": 0.0
    },
    {
      "x": -3.34,
      "y": 1.2599999999999998,
      "yaw": 0.0
    },
    {
      "x": -3.460000000000001,
      "y": 1.379999999999999,
      "yaw": 0.0
    },
    {
      "x": -3.58,
      "y": 1.5,
      "yaw": 0.0
    },
    {
      "x": -3.700000000000001,
      "y": 1.6199999999999992,
      "yaw": 0.0
    },
    {
      "x": -3.8200000000000003,
      "y": 1.7400000000000002,
      "yaw": 0.0
    },
    {
      "x": -3.9399999999999995,
      "y": 1.8599999999999994,
      "yaw": 0.0
    },
    {
      "x": -4.0600000000000005,
      "y": 1.9800000000000004,
      "yaw": 0.0
    },
    {
      "x": -4.18,
      "y": 2.0999999999999996,
      "yaw": 0.0
    },
    {
      "x": -4.300000000000001,
      "y": 2.219999999999999,
      "yaw": 0.0
    },
    {
      "x": -4.42,
      "y": 2.34,
      "yaw": 0.0
    },
    {
      "x": -4.540000000000001,
      "y": 2.459999999999999,
      "yaw": 0.0
    },
    {
      "x": -4.66,
      "y": 2.58,
      "yaw": 0.0
    },
    {
      "x": -4.780000000000001,
      "y": 2.6999999999999993,
      "yaw": 0.0
    },
    {
      "x": -4.9,
      "y": 2.8200000000000003,
      "yaw": 0.0
    },
    {
      "x": -5.0200000000000005,
      "y": 2.9399999999999995,
      "yaw": 0.0
    },
    {
      "x": -5.140000000000001,
      "y": 3.0599999999999987,
      "yaw": 0.0
    },
    {
      "x": -5.260000000000001,
      "y": 3.1799999999999997,
      "yaw": 0.0
    },
    {
      "x": -5.38,
      "y": 3.299999999999999,
      "yaw": 0.0
    },
    {
      "x": -5.5,
      "y": 3.42,
      "yaw": 0.0
    },
    {
      "x": -5.62,
      "y": 3.539999999999999,
      "yaw": 0.0
    },
    {
      "x": -5.74,
      "y": 3.66,
      "yaw": 0.0
    },
    {
      "x": -5.86,
      "y": 3.7799999999999994,
      "yaw": 0.0
    },
    {
      "x": -5.98,
      "y": 3.9000000000000004,
      "yaw": 0.0
    },
    {
      "x": -6.1000000000000005,
      "y": 4.02,
      "yaw": 0.0
    },
    {
      "x": -6.220000000000001,
      "y": 4.139999999999999,
      "yaw": 0.0
    },
    {
      "x": -6.34,
      "y": 4.139999999999999,
      "yaw": 0.0
    },
    {
      "x": -6.46,
      "y": 4.139999999999999,
      "yaw": 0.0
    },
    {
      "x": -6.58,
      "y": 4.139999999999999,
      "yaw": 0.0
    },
    {
      "x": -6.7,
      "y": 4.26,
      "yaw": 0.0
    },
    {
      "x": -6.82,
      "y": 4.379999999999999,
      "yaw": 0.0
    },
    {
      "x": -6.94,
      "y": 4.5,
      "yaw": 0.0
    },
    {
      "x": -7.0600000000000005,
      "y": 4.619999999999999,
      "yaw": 0.0
    },
    {
      "x": -7.180000000000001,
      "y": 4.74,
      "yaw": 0.0
    },
    {
      "x": -7.3,
      "y": 4.859999999999999,
      "yaw": 0.0
    },
    {
      "x": -7.42,
      "y": 4.979999999999999,
      "yaw": 0.0
    },
    {
      "x": -7.54,
      "y": 5.1,
      "yaw": 0.0
    },
    {
      "x": -7.66,
      "y": 5.219999999999999,
      "yaw": 0.0
    },
    {
      "x": -7.78,
      "y": 5.34,
      "yaw": 0.0
    },
    {
      "x": -7.9,
      "y": 5.459999999999999,
      "yaw": 0.0
    },
    {
      "x": -8.02,
      "y": 5.58,
      "yaw": 0.0
    },
    {
      "x": -8.14,
      "y": 5.58,
      "yaw": 0.0
    },
    {
      "x": -8.26,
      "y": 5.58,
      "yaw": 0.0
    },
    {
      "x": -8.379999999999999,
      "y": 5.58,
      "yaw": 0.0
    },
    {
      "x": -8.5,
      "y": 5.58,
      "yaw": 0.0
    },
    {
      "x": -8.620000000000001,
      "y": 5.58,
      "yaw": 0.0
    },
    {
      "x": -8.74,
      "y": 5.58,
      "yaw": 0.0
    },
    {
      "x": -8.86,
      "y": 5.58,
      "yaw": 0.0
    },
    {
      "x": -8.98,
      "y": 5.58,
      "yaw": 0.0
    },
    {
      "x": -9.1,
      "y": 5.58,
      "yaw": 0.0
    },
    {
      "x": -9.22,
      "y": 5.699999999999999,
      "yaw": 0.0
    },
    {
      "x": -9.34,
      "y": 5.82,
      "yaw": 0.0
    },
    {
      "x": -9.46,
      "y": 5.9399999999999995,
      "yaw": 0.0
    },
    {
      "x": -9.58,
      "y": 6.059999999999999,
      "yaw": 0.0
    },
    {
      "x": -9.7,
      "y": 6.18,
      "yaw": 0.0
    },
    {
      "x": -9.82,
      "y": 6.299999999999999,
      "yaw": 0.0
    },
    {
      "x": -9.94,
      "y": 6.42,
      "yaw": 0.0
    },
    {
      "x": -10.06,
      "y": 6.539999999999999,
      "yaw": 0.0
    },
    {
      "x": -10.18,
      "y": 6.66,
      "yaw": 0.0
    },
    {
      "x": -10.3,
      "y": 6.779999999999999,
      "yaw": 0.0
    },
    {
      "x": -10.42,
      "y": 6.899999999999999,
      "yaw": 0.0
    },
    {
      "x": -10.54,
      "y": 7.02,
      "yaw": 0.0
    },
    {
      "x": -10.66,
      "y": 7.140000000000001,
      "yaw": 0.0
    },
    {
      "x": -10.780000000000001,
      "y": 7.259999999999998,
      "yaw": 0.0
    },
    {
      "x": -10.9,
      "y": 7.379999999999999,
      "yaw": 0.0
    },
    {
      "x": -11.02,
      "y": 7.5,
      "yaw": 0.0
    },
    {
      "x": -11.14,
      "y": 7.620000000000001,
      "yaw": 0.0
    },
    {
      "x": -11.26,
      "y": 7.739999999999998,
      "yaw": 0.0
    },
    {
      "x": -11.38,
      "y": 7.859999999999999,
      "yaw": 0.0
    },
    {
      "x": -11.5,
      "y": 7.859999999999999,
      "yaw": 0.0
    },
    {
      "x": -11.620000000000001,
      "y": 7.98,
      "yaw": 0.0
    },
    {
      "x": -11.74,
      "y": 7.98,
      "yaw": 0.0
    },
    {
      "x": -11.86,
      "y": 8.099999999999998,
      "yaw": 0.0
    },
    {
      "x": -11.98,
      "y": 8.099999999999998,
      "yaw": 0.0
    },
    {
      "x": -12.1,
      "y": 8.219999999999999,
      "yaw": 0.0
    },
    {
      "x": -12.22,
      "y": 8.219999999999999,
      "yaw": 0.0
    }
  ],
  "products": {
    "ProductB": {
      "pickup": {
        "x": 5.0,
        "y": 0.7270986072475832,
        "yaw": 1.5707963267948966
      },
      "slot": {
        "x": 5.0,
        "y": 1.8070986072475832,
        "z": 1.38
      },
      "storage": "shelf_18"
    },
    "ProductC": {
      "pickup": {
        "x": -1.4,
        "y": 3.314577738546664,
        "yaw": 1.5707963267948966
      },
      "slot": {
        "x": -1.4,
        "y": 4.394577738546664,
        "z": 1.38
      },
      "storage": "shelf_21"
    },
    "ProductG": {
      "pickup": {
        "x": -7.8,
        "y": -4.463935080814976,
        "yaw": -1.5707963267948966
      },
      "slot": {
        "x": -7.8,
        "y": -5.543935080814976,
        "z": 1.38
      },
      "storage": "shelf_1"
    },
    "ProductR": {
      "pickup": {
        "x": 1.8,
        "y": 0.8057451235228793,
        "yaw": 1.5707963267948966
      },
      "slot": {
        "x": 1.8,
        "y": 1.8857451235228793,
        "z": 1.38
      },
      "storage": "shelf_17"
    },
    "ProductY": {
      "pickup": {
        "x": 8.2,
        "y": 3.402030629023027,
        "yaw": 1.5707963267948966
      },
      "slot": {
        "x": 8.2,
        "y": 4.4820306290230265,
        "z": 1.38
      },
      "storage": "shelf_23"
    }
  },
  "resolution": 0.12,
  "robot": {
    "x": 0.379999999999999,
    "y": -7.62,
    "yaw": 1.5707963267948966
  },
  "status": "mapping",
  "task": null,
  "true_obstacles": [
    {
      "kind": "wall",
      "name": "front_wall",
      "x1": -13.0,
      "x2": 13.0,
      "y1": -9.0,
      "y2": -8.82
    },
    {
      "kind": "wall",
      "name": "back_wall",
      "x1": -13.0,
      "x2": 13.0,
      "y1": 8.82,
      "y2": 9.0
    },
    {
      "kind": "wall",
      "name": "left_wall",
      "x1": -13.0,
      "x2": -12.82,
      "y1": -9.0,
      "y2": 9.0
    },
    {
      "kind": "wall",
      "name": "right_wall",
      "x1": 12.82,
      "x2": 13.0,
      "y1": -9.0,
      "y2": 9.0
    },
    {
      "kind": "shelf",
      "name": "shelf_1",
      "x1": -8.771234986764133,
      "x2": -6.828765013235866,
      "y1": -6.236064919185023,
      "y2": -5.363935080814977
    },
    {
      "kind": "shelf",
      "name": "shelf_2",
      "x1": -5.4764994779765495,
      "x2": -3.72350052202345,
      "y1": -6.171123364025502,
      "y2": -5.428876635974498
    },
    {
      "kind": "shelf",
      "name": "shelf_3",
      "x1": -2.307881662289401,
      "x2": -0.49211833771059865,
      "y1": -6.1773633475739125,
      "y2": -5.422636652426087
    },
    {
      "kind": "shelf",
      "name": "shelf_4",
      "x1": 7.1825732083618385,
      "x2": 9.217426791638161,
      "y1": -6.136167817067502,
      "y2": -5.463832182932498
    },
    {
      "kind": "shelf",
      "name": "shelf_5",
      "x1": -5.564752306140099,
      "x2": -3.6352476938599,
      "y1": -3.564684990545397,
      "y2": -2.8353150094546034
    },
    {
      "kind": "shelf",
      "name": "shelf_6",
      "x1": 0.8699495717751935,
      "x2": 2.7300504282248066,
      "y1": -3.5198167431180503,
      "y2": -2.88018325688195
    },
    {
      "kind": "shelf",
      "name": "shelf_7",
      "x1": 4.167666925269733,
      "x2": 5.832333074730267,
      "y1": -3.629263569203032,
      "y2": -2.770736430796968
    },
    {
      "kind": "shelf",
      "name": "shelf_8",
      "x1": 7.196631814139172,
      "x2": 9.203368185860827,
      "y1": -3.511838508687434,
      "y2": -2.8881614913125664
    },
    {
      "kind": "shelf",
      "name": "shelf_9",
      "x1": -8.660195501940297,
      "x2": -6.939804498059702,
      "y1": -1.0375388907758507,
      "y2": -0.16246110922414925
    },
    {
      "kind": "shelf",
      "name": "shelf_10",
      "x1": -5.489466510592308,
      "x2": -3.7105334894076907,
      "y1": -0.97934772403904,
      "y2": -0.22065227596095988
    },
    {
      "kind": "shelf",
      "name": "shelf_11",
      "x1": -2.4213296164902767,
      "x2": -0.37867038350972315,
      "y1": -0.9894903445724385,
      "y2": -0.2105096554275615
    },
    {
      "kind": "shelf",
      "name": "shelf_12",
      "x1": 0.8024266221644061,
      "x2": 2.797573377835594,
      "y1": -1.002956939928286,
      "y2": -0.19704306007171402
    },
    {
      "kind": "shelf",
      "name": "shelf_13",
      "x1": 4.054964323653029,
      "x2": 5.945035676346971,
      "y1": -0.991261805352767,
      "y2": -0.20873819464723298
    },
    {
      "kind": "shelf",
      "name": "shelf_14",
      "x1": 7.4954604966918605,
      "x2": 8.904539503308138,
      "y1": -1.0331632929453527,
      "y2": -0.16683670705464726
    },
    {
      "kind": "shelf",
      "name": "shelf_15",
      "x1": -5.586181685214317,
      "x2": -3.613818314785682,
      "y1": 1.6669248410211965,
      "y2": 2.3330751589788035
    },
    {
      "kind": "shelf",
      "name": "shelf_16",
      "x1": -2.1998531282296647,
      "x2": -0.600146871770335,
      "y1": 1.621784553767306,
      "y2": 2.3782154462326943
    },
    {
      "kind": "shelf",
      "name": "shelf_17",
      "x1": 0.9500285020252055,
      "x2": 2.6499714979747946,
      "y1": 1.7057451235228793,
      "y2": 2.2942548764771207
    },
    {
      "kind": "shelf",
      "name": "shelf_18",
      "x1": 4.038573906916306,
      "x2": 5.961426093083694,
      "y1": 1.6270986072475833,
      "y2": 2.3729013927524165
    },
    {
      "kind": "shelf",
      "name": "shelf_19",
      "x1": 7.3953042907249245,
      "x2": 9.004695709275074,
      "y1": 1.668618213360925,
      "y2": 2.3313817866390747
    },
    {
      "kind": "shelf",
      "name": "shelf_20",
      "x1": -8.683131103555143,
      "x2": -6.916868896444856,
      "y1": 4.281024207365209,
      "y2": 4.91897579263479
    },
    {
      "kind": "shelf",
      "name": "shelf_21",
      "x1": -2.308796104629144,
      "x2": -0.4912038953708556,
      "y1": 4.214577738546664,
      "y2": 4.985422261453335
    },
    {
      "kind": "shelf",
      "name": "shelf_22",
      "x1": 0.7896440118749106,
      "x2": 2.8103559881250897,
      "y1": 4.2345641540880905,
      "y2": 4.965435845911909
    },
    {
      "kind": "shelf",
      "name": "shelf_23",
      "x1": 7.378725153235758,
      "x2": 9.021274846764241,
      "y1": 4.302030629023027,
      "y2": 4.8979693709769725
    },
    {
      "kind": "shelf",
      "name": "shelf_24",
      "x1": -8.478223619553097,
      "x2": -7.121776380446903,
      "y1": 6.1629552892333335,
      "y2": 7.037044710766666
    },
    {
      "kind": "shelf",
      "name": "shelf_25",
      "x1": -5.609802806609165,
      "x2": -3.590197193390834,
      "y1": 6.170664925363512,
      "y2": 7.029335074636487
    },
    {
      "kind": "shelf",
      "name": "shelf_26",
      "x1": 7.321860174772116,
      "x2": 9.078139825227883,
      "y1": 6.20764220555386,
      "y2": 6.992357794446139
    },
    {
      "kind": "crate",
      "name": "pallet_stack_1",
      "x1": -5.320889655004969,
      "x2": -4.826648373611619,
      "y1": -4.4549796692882335,
      "y2": -3.960738387894884
    },
    {
      "kind": "crate",
      "name": "pallet_stack_2",
      "x1": -0.22348027871973883,
      "x2": 0.25841820861628195,
      "y1": 5.911969567926967,
      "y2": 6.393868055262988
    },
    {
      "kind": "crate",
      "name": "pallet_stack_3",
      "x1": -4.230556166439621,
      "x2": -3.7113868053155645,
      "y1": 3.702993862160765,
      "y2": 4.222163223284822
    },
    {
      "kind": "crate",
      "name": "pallet_stack_4",
      "x1": -5.55517834225278,
      "x2": -5.033939522709361,
      "y1": -6.84297479636776,
      "y2": -6.321735976824342
    },
    {
      "kind": "crate",
      "name": "pallet_stack_6",
      "x1": -1.4136061654318892,
      "x2": -0.7544766154224095,
      "y1": -6.837125999187537,
      "y2": -6.177996449178057
    },
    {
      "kind": "crate",
      "name": "pallet_stack_7",
      "x1": -3.5228823339050437,
      "x2": -2.8998261787763595,
      "y1": -2.184080588894299,
      "y2": -1.5610244337656147
    },
    {
      "kind": "crate",
      "name": "pallet_stack_8",
      "x1": -6.571520659491902,
      "x2": -6.034046018851348,
      "y1": -6.771762397697651,
      "y2": -6.234287757057097
    },
    {
      "kind": "crate",
      "name": "pallet_stack_9",
      "x1": -0.7045350791244859,
      "x2": -0.20946265085231328,
      "y1": -5.333743496572062,
      "y2": -4.83867106829989
    },
    {
      "kind": "crate",
      "name": "pallet_stack_10",
      "x1": -1.1600321988077131,
      "x2": -0.5829299916120577,
      "y1": 5.974510923222735,
      "y2": 6.551613130418391
    },
    {
      "kind": "crate",
      "name": "pallet_stack_11",
      "x1": 8.696626723252486,
      "x2": 9.158287542051674,
      "y1": -5.4301522578827495,
      "y2": -4.968491439083563
    },
    {
      "kind": "crate",
      "name": "pallet_stack_12",
      "x1": 4.215670026491188,
      "x2": 4.778688335013222,
      "y1": 5.054299477969374,
      "y2": 5.617317786491408
    },
    {
      "kind": "crate",
      "name": "pallet_stack_13",
      "x1": 2.3909535827090993,
      "x2": 3.0009792681449907,
      "y1": -1.6878354032061083,
      "y2": -1.0778097177702168
    },
    {
      "kind": "crate",
      "name": "pallet_stack_14",
      "x1": 8.934754805661797,
      "x2": 9.441988773266047,
      "y1": -6.724252568373294,
      "y2": -6.217018600769042
    },
    {
      "kind": "crate",
      "name": "pallet_stack_15",
      "x1": 4.291987365532077,
      "x2": 4.745517145342343,
      "y1": 6.054770377300405,
      "y2": 6.5083001571106704
    },
    {
      "kind": "crate",
      "name": "pallet_stack_16",
      "x1": 1.756028516762925,
      "x2": 2.332357032548614,
      "y1": 3.5709464189292075,
      "y2": 4.147274934714896
    }
  ],
  "updated_at": "2026-05-10 11:24:33",
  "width_m": 26.0
}